watchmen_indicator_surface/__init__.py
watchmen_indicator_surface/data/__init__.py
watchmen_indicator_surface/data/convergence_data_router.py
watchmen_indicator_surface/data/objective_data_router.py
watchmen_indicator_surface/main.py
watchmen_indicator_surface/meta/__init__.py
watchmen_indicator_surface/meta/achievement_plugin_task_router.py
watchmen_indicator_surface/meta/bucket_router.py
watchmen_indicator_surface/meta/convergence_router.py
watchmen_indicator_surface/meta/derived_objective_report_router.py
watchmen_indicator_surface/meta/derived_objective_router.py
watchmen_indicator_surface/meta/indicator_router.py
watchmen_indicator_surface/meta/objective_report_router.py
watchmen_indicator_surface/meta/objective_router.py
watchmen_indicator_surface/meta/subject_router.py
watchmen_indicator_surface/servcie/__init__.py
watchmen_indicator_surface/servcie/objective_analysis_service.py
watchmen_indicator_surface/settings.py
watchmen_indicator_surface/util/__init__.py
watchmen_indicator_surface/util/trans.py
watchmen_indicator_surface-18.0.1.dist-info/METADATA
watchmen_indicator_surface-18.0.1.dist-info/WHEEL
watchmen_indicator_surface-18.0.1.dist-info/RECORD
